raser/__init__.py
raser/calcurrent.py
raser/elereadout.py
raser/g4particles.py
raser/geometry.py
raser/pyfenics.py
raser/setting.py
raser-0.2.1.dist-info/LICENSE
raser-0.2.1.dist-info/METADATA
raser-0.2.1.dist-info/WHEEL
raser-0.2.1.dist-info/top_level.txt
raser-0.2.1.dist-info/RECORD
