Metadata-Version: 2.1
Name: raser
Version: 0.2.1
Summary: Simulate timing resolution, TCT, TPA-TCT of 2D&3D Si&SiC detector
Home-page: https://github.com/dt-np/raser
Author: Xin Shi
Author-email: XXX@example.com
License: UNKNOWN
Platform: UNKNOWN
Classifier: Programming Language :: Python :: 3
Classifier: License :: OSI Approved :: MIT License
Classifier: Operating System :: OS Independent
